cv_recon/__init__.py
cv_recon/cv_tools.py
cv_recon/picam_example.py
cv_recon/picam/__init__.py
cv_recon/picam/picam.py
cv_recon/recon/__init__.py
cv_recon/recon/colorspace.py
cv_recon/recon/features.py
cv_recon-1.0.0.dist-info/LICENSE
cv_recon-1.0.0.dist-info/METADATA
cv_recon-1.0.0.dist-info/WHEEL
cv_recon-1.0.0.dist-info/top_level.txt
cv_recon-1.0.0.dist-info/RECORD
