Metadata-Version: 2.1
Name: cv-recon
Version: 1.0.0
Summary: A computer vision toolkit focused on color detection and feature matching using OpenCV. It allows you to easily start the picamera in case you're using a Raspberry PI.
Home-page: https://github.com/AguilarLagunasArturo/cv-recon
Author: Arturo Aguilar Lagunas
Author-email: aguilar.lagunas.arturo@gmail.com
License: UNKNOWN
Keywords: opencv,color detection,feature matching,computer vision,hsv,picamera,raspberry pi
Platform: UNKNOWN
Classifier: Development Status :: 5 - Production/Stable
Classifier: Programming Language :: Python
Classifier: Programming Language :: Python :: 3
Classifier: License :: OSI Approved :: MIT License
Classifier: Operating System :: OS Independent
License-File: LICENSE
